odoo9_addon_report_wkhtmltopdf_param-9.0.1.0.0-py2.7-nspkg.pth
odoo9_addon_report_wkhtmltopdf_param-9.0.1.0.0.dist-info/DESCRIPTION.rst
odoo9_addon_report_wkhtmltopdf_param-9.0.1.0.0.dist-info/METADATA
odoo9_addon_report_wkhtmltopdf_param-9.0.1.0.0.dist-info/RECORD
odoo9_addon_report_wkhtmltopdf_param-9.0.1.0.0.dist-info/WHEEL
odoo9_addon_report_wkhtmltopdf_param-9.0.1.0.0.dist-info/metadata.json
odoo9_addon_report_wkhtmltopdf_param-9.0.1.0.0.dist-info/namespace_packages.txt
odoo9_addon_report_wkhtmltopdf_param-9.0.1.0.0.dist-info/top_level.txt
odoo_addons/report_wkhtmltopdf_param/README.rst
odoo_addons/report_wkhtmltopdf_param/__init__.py
odoo_addons/report_wkhtmltopdf_param/__openerp__.py
odoo_addons/report_wkhtmltopdf_param/models/__init__.py
odoo_addons/report_wkhtmltopdf_param/models/report.py
odoo_addons/report_wkhtmltopdf_param/models/report_paperformat.py
odoo_addons/report_wkhtmltopdf_param/models/report_paperformat_parameter.py
odoo_addons/report_wkhtmltopdf_param/security/ir.model.access.csv
odoo_addons/report_wkhtmltopdf_param/static/description/icon.png
odoo_addons/report_wkhtmltopdf_param/tests/__init__.py
odoo_addons/report_wkhtmltopdf_param/tests/test_report_paperformat.py
odoo_addons/report_wkhtmltopdf_param/views/paperformat.xml
